orbis_plugin_aggregation_local_cache/__init__.py
orbis_plugin_aggregation_local_cache/main.py
orbis_plugin_aggregation_local_cache-2.3.1.dist-info/LICENSE
orbis_plugin_aggregation_local_cache-2.3.1.dist-info/METADATA
orbis_plugin_aggregation_local_cache-2.3.1.dist-info/WHEEL
orbis_plugin_aggregation_local_cache-2.3.1.dist-info/top_level.txt
orbis_plugin_aggregation_local_cache-2.3.1.dist-info/RECORD
