Metadata-Version: 2.1
Name: orbis-plugin-aggregation-local-cache
Version: 2.3.1
Summary: The local_cache aggregation plugin for Orbis
Home-page: https://github.com/orbis-eval/orbis_plugin_aggregation_local_cache
Author: fabod
License: GPL2
Platform: UNKNOWN
Requires-Python: >3.6
